README.rst
setup.cfg
setup.py
freezedata/__init__.py
freezedata/freezedata.py
freezedata.egg-info/PKG-INFO
freezedata.egg-info/SOURCES.txt
freezedata.egg-info/dependency_links.txt
freezedata.egg-info/top_level.txt
test/test_freezedata.py